enviRobot_scoop/__init__.py
enviRobot_scoop/aiot_screenshot.py
enviRobot_scoop/enviRobot_scoop.py
enviRobot_scoop/gpt.py
enviRobot_scoop/plotly_screenshot.py
enviRobot_scoop/upload_to_imgur.py
enviRobot_scoop-0.1.6.dist-info/LICENSE
enviRobot_scoop-0.1.6.dist-info/METADATA
enviRobot_scoop-0.1.6.dist-info/WHEEL
enviRobot_scoop-0.1.6.dist-info/top_level.txt
enviRobot_scoop-0.1.6.dist-info/RECORD
