Metadata-Version: 2.1
Name: enviRobot-scoop
Version: 0.1.6
Summary: enviRobot service that can be held by Scoop.
Home-page: https://github.com/bohachu/ask_enviRobot
Author: JcXGTcW
Author-email: jcxgtcw@cameo.tw
Classifier: Programming Language :: Python :: 3
Classifier: License :: OSI Approved :: MIT License
Classifier: Operating System :: OS Independent
Requires-Python: >=3.6
License-File: LICENSE
Requires-Dist: fastapi ==0.63.0
Requires-Dist: uvicorn ==0.13.4
Requires-Dist: openai ==0.27.4
Requires-Dist: geocoder ==1.38.1
Requires-Dist: line-bot-sdk ==2.4.2
Requires-Dist: pandas ==1.5.3
Requires-Dist: geopy ==2.3.0
Requires-Dist: selenium ==4.7.2
Requires-Dist: pyimgur ==0.6.0
Requires-Dist: pyyaml ==6.0
Requires-Dist: python-dotenv ==0.15.0
Requires-Dist: plotly ==5.15.0
Requires-Dist: kaleido ==0.2.1
